{
  "projectPath": ".",
  "outputPath": "aspirate-output",
  "namespace": "ps-info",
  "containerRegistry": "registry.versonium.cloud",
  "containerImageTags": [
    "v0.1.2"
  ],
  "imagePullPolicy": "IfNotPresent",
  "containerBuilder": "docker",
  "containerRepositoryPrefix": "ps-info",
  "outputFormat": "kustomize",
  "skipFinalKustomizeGeneration": false,
  "privateRegistryUrl": "https://registry.versonium.cloud",
  "privateRegistryEmail": "aspir8@aka.ms",
  "withPrivateRegistry": true,
  "includeDashboard": true,
  "useCustomNamespace": true,
  "secrets": {
    "salt": "onnLqfJH/3GVsFUS",
    "hash": "YIvXXOUqBedJ\u002BpIGb4/hAXZ9HsR5e25Q5YVV58r1Waw=",
    "secrets": {
      "mysql-server-password": {
        "value": "onnLqfJH/3GVsFUSfpnvwJWaLf7TmcbZP5mdVF86xkXAGp\u002BF4IJq3BMnUm5RR9Kbx7I="
      },
      "mysql-server": {},
      "mysql-server-phpmyadmin": {},
      "ps-info-database": {},
      "apis": {
        "ConnectionStrings__ps-info-database": "onnLqfJH/3GVsFUSgdKQeCeZuzMT1zo2mNJg8GkYwgvnEOq5\u002BL5q\u002BUgwVntSesKT/OiLOQznk9WfhS55RRfweeVmls\u002B0K5TQ3Wn4Jff/r63XmrNzrUfmwVtvYdKpcFv9cSbTsQmv4Z95ynYBVvOhrsvyCRLMLj4="
      },
      "application": {}
    }
  },
  "processAllComponents": true
}